p1_data_client_python/__init__.py
p1_data_client_python/abstract_client.py
p1_data_client_python/client.py
p1_data_client_python/exceptions.py
p1_data_client_python/version.py
p1_data_client_python/edgar/__init__.py
p1_data_client_python/edgar/config.py
p1_data_client_python/edgar/edgar_client.py
p1_data_client_python/edgar/mappers.py
p1_data_client_python/edgar/utils.py
p1_data_client_python/helpers/datetime_.py
p1_data_client_python/helpers/dbg.py
p1_data_client_python/helpers/git.py
p1_data_client_python/helpers/io_.py
p1_data_client_python/helpers/printing.py
p1_data_client_python/helpers/system_interaction.py
p1_data_client_python/helpers/unit_test.py
p1_data_client_python-1.8.2.dist-info/METADATA
p1_data_client_python-1.8.2.dist-info/WHEEL
p1_data_client_python-1.8.2.dist-info/top_level.txt
p1_data_client_python-1.8.2.dist-info/RECORD
