Metadata-Version: 2.1
Name: p1-data-client-python
Version: 1.8.2
Summary: Package for P1 Data API access
Home-page: https://github.com/ParticleDev/p1_data_client
Author: ParticleOne inc.
Author-email: malanin@particle.one
Maintainer: 
Maintainer-email: 
License: MIT
Project-URL: Site, https://particle.one/
Project-URL: API registration, https://particle.one/api-access
Keywords: p1_data_client_python,API,data,financial,economic,particle,particleone,particle.one
Platform: UNKNOWN
Classifier: Intended Audience :: Developers
Classifier: License :: OSI Approved :: MIT License
Classifier: Operating System :: OS Independent
Classifier: Programming Language :: Python :: 3.7
Classifier: Programming Language :: Python :: 3.8
Requires-Python: >= 3.7
Requires-Dist: pandas (>=1.0.0)
Requires-Dist: requests (>=2.18.0)
Requires-Dist: tqdm (>=4.50.0)
Requires-Dist: halo (>=0.0.31)
